example_fastapi_usage/__init__.py
example_fastapi_usage/app.py
example_fastapi_usage/models/__init__.py
example_fastapi_usage/models/book.py
example_fastapi_usage/repositories/__init__.py
example_fastapi_usage/repositories/book_repository.py
example_fastapi_usage/routes/__init__.py
example_fastapi_usage/routes/v1/__init__.py
example_fastapi_usage/routes/v1/book_router.py
example_fastapi_usage/schemas/__init__.py
example_fastapi_usage/schemas/book_schemas.py
example_fastapi_usage/services/__init__.py
example_fastapi_usage/services/book_service.py
fastapi_dream_core/__init__.py
fastapi_dream_core/__version__.py
fastapi_dream_core/base_repository.py
fastapi_dream_core/constants.py
fastapi_dream_core/model_mixin.py
fastapi_dream_core/pagination.py
fastapi_dream_core-0.0.6.dist-info/LICENSE
fastapi_dream_core-0.0.6.dist-info/METADATA
fastapi_dream_core-0.0.6.dist-info/WHEEL
fastapi_dream_core-0.0.6.dist-info/top_level.txt
fastapi_dream_core-0.0.6.dist-info/RECORD
