Metadata-Version: 2.1
Name: fastapi-dream-core
Version: 0.0.6
Summary: Reusable core, repositories and utilities for FastAPI
Home-page: https://github.com/yurihartmann/fastapi_dream_core
Author: Yuri Hartmann
Author-email: yurihartmann0607@gmail.com
License: MIT
Platform: UNKNOWN
Classifier: License :: OSI Approved :: MIT License
Classifier: Programming Language :: Python
Classifier: Programming Language :: Python :: 3
Classifier: Programming Language :: Python :: 3.6
Classifier: Programming Language :: Python :: Implementation :: CPython
Classifier: Programming Language :: Python :: Implementation :: PyPy
Requires-Python: >=3.6.0
License-File: LICENSE
Requires-Dist: fastapi (>=0.65.0)
Requires-Dist: pydantic (>=1.8.0)
Requires-Dist: sqlalchemy (>=1.4.0)
Requires-Dist: sqlmodel (>=0.0.4)
